evo/blockmodels/__init__.py
evo/blockmodels/_model_config.py
evo/blockmodels/_types.py
evo/blockmodels/_utils.py
evo/blockmodels/client.py
evo/blockmodels/data.py
evo/blockmodels/exceptions.py
evo/blockmodels/io.py
evo/blockmodels/endpoints/__init__.py
evo/blockmodels/endpoints/models.py
evo/blockmodels/endpoints/api/__init__.py
evo/blockmodels/endpoints/api/column_operations_api.py
evo/blockmodels/endpoints/api/jobs_api.py
evo/blockmodels/endpoints/api/metadata_api.py
evo/blockmodels/endpoints/api/operations_api.py
evo/blockmodels/endpoints/api/reports_api.py
evo/blockmodels/endpoints/api/units_api.py
evo/blockmodels/endpoints/api/versions_api.py
evo_blockmodels-0.1.1.dist-info/METADATA
evo_blockmodels-0.1.1.dist-info/WHEEL
evo_blockmodels-0.1.1.dist-info/licenses/LICENSE.md
evo_blockmodels-0.1.1.dist-info/RECORD
