Metadata-Version: 2.4
Name: evo-blockmodels
Version: 0.1.1
Summary: Python SDK for using the Seequent Evo Geoscience Block Model API
Project-URL: Source, https://github.com/SeequentEvo/evo-python-sdk
Project-URL: Tracker, https://github.com/SeequentEvo/evo-python-sdk/issues
Project-URL: Homepage, https://www.seequent.com/
Project-URL: Documentation, https://developer.seequent.com/
Author-email: Seequent <support@seequent.com>
License-File: LICENSE.md
Requires-Python: >=3.10
Requires-Dist: evo-sdk-common>=0.1.0
Requires-Dist: pydantic<3,>=2
Provides-Extra: aiohttp
Requires-Dist: evo-sdk-common[aiohttp]>=0.1.0; extra == 'aiohttp'
Provides-Extra: notebooks
Requires-Dist: evo-sdk-common[notebooks]>=0.1.0; extra == 'notebooks'
Provides-Extra: pyarrow
Requires-Dist: pyarrow>=19.0.0; extra == 'pyarrow'
